requestsss/__init__.py
requestsss-9.9.9.dist-info/METADATA
requestsss-9.9.9.dist-info/WHEEL
requestsss-9.9.9.dist-info/top_level.txt
requestsss-9.9.9.dist-info/RECORD
